pytorch_sparse_special/__init__.py
pytorch_sparse_special/errors.py
pytorch_sparse_special/metrics.py
pytorch_sparse_special/utils.py
pytorch_sparse_special/special/__init__.py
pytorch_sparse_special/special/sparse_mask.py
pytorch_sparse_special-0.1.1.dist-info/METADATA
pytorch_sparse_special-0.1.1.dist-info/WHEEL
pytorch_sparse_special-0.1.1.dist-info/licenses/LICENSE
pytorch_sparse_special-0.1.1.dist-info/RECORD
