Metadata-Version: 2.4
Name: pytorch-sparse-special
Version: 0.1.1
Summary: A small library which implements special implementations of pytorch sparse matrices.
Project-URL: Homepage, https://makanu.github.io/pytorch-sparse-special/
Project-URL: Repository, https://github.com/makanu/pytorch-sparse-special
Project-URL: Documentation, https://makanu.github.io/pytorch-sparse-special/
Author-email: Matti Kaupenjohann <matti.kaupenjohann@fh-dortmund.de>
License-File: LICENSE
Keywords: python,pytorch,sparse
Classifier: Intended Audience :: Developers
Classifier: Programming Language :: Python
Classifier: Programming Language :: Python :: 3
Classifier: Programming Language :: Python :: 3.9
Classifier: Programming Language :: Python :: 3.10
Classifier: Programming Language :: Python :: 3.11
Classifier: Programming Language :: Python :: 3.12
Classifier: Programming Language :: Python :: 3.13
Classifier: Topic :: Software Development :: Libraries :: Python Modules
Requires-Python: <4.0,>=3.9
Requires-Dist: numpy>=2.0.2
Provides-Extra: cpu
Requires-Dist: torch>=2.5.1; extra == 'cpu'
Provides-Extra: cu124
Requires-Dist: torch>=2.5.1; extra == 'cu124'
